cl_keeper/__init__.py
cl_keeper/__main__.py
cl_keeper/_version.py
cl_keeper/app.py
cl_keeper/check.py
cl_keeper/config.py
cl_keeper/context.py
cl_keeper/fix.py
cl_keeper/model.py
cl_keeper/parse.py
cl_keeper/py.typed
cl_keeper/render.py
cl_keeper/sort.py
cl_keeper/typing.py
cl_keeper/vcs.py
cl_keeper-0.0.0b3.dist-info/licenses/LICENSE
cl_keeper-0.0.0b3.dist-info/METADATA
cl_keeper-0.0.0b3.dist-info/WHEEL
cl_keeper-0.0.0b3.dist-info/entry_points.txt
cl_keeper-0.0.0b3.dist-info/top_level.txt
cl_keeper-0.0.0b3.dist-info/RECORD
